html_similarity/__init__.py
html_similarity/similarity.py
html_similarity/structural_similarity.py
html_similarity/style_similarity.py
html_similarity-0.3.3.dist-info/LICENSE
html_similarity-0.3.3.dist-info/METADATA
html_similarity-0.3.3.dist-info/WHEEL
html_similarity-0.3.3.dist-info/top_level.txt
html_similarity-0.3.3.dist-info/RECORD
