Metadata-Version: 1.2
Name: html-similarity
Version: 0.3.3
Summary: A set of similarity metricts to compare html files.
Home-page: https://github.com/matiskay/html-similarity
Author: Edgar Marca
Author-email: matiskay@gmail.com
Maintainer: Edgar Marca
Maintainer-email: matiskay@gmail.com
License: BSD
Platform: UNKNOWN
Classifier: Intended Audience :: Developers
Classifier: License :: OSI Approved :: BSD License
Classifier: Programming Language :: Python :: 3.6
Classifier: Topic :: Software Development :: Libraries :: Python Modules
